tests/__init__.py
tests/conftest.py
tests/test_armory.py
tests/test_config.py
tests/test_phantom.py
yapam/__init__.py
yapam/armory.py
yapam/config.py
yapam/phantom.py
yapam-0.1.5.dist-info/LICENSE
yapam-0.1.5.dist-info/METADATA
yapam-0.1.5.dist-info/WHEEL
yapam-0.1.5.dist-info/top_level.txt
yapam-0.1.5.dist-info/RECORD
