Metadata-Version: 2.1
Name: yapam
Version: 0.1.5
Summary: Yet another ammo maker
Home-page: https://github.com/devalv/yapam
Author: Devyatkin Aleksei
Author-email: yapam@devyatkin.dev
License: UNKNOWN
Platform: UNKNOWN
Classifier: Programming Language :: Python :: 3
Classifier: License :: OSI Approved :: MIT License
Classifier: Operating System :: POSIX :: Linux
Requires-Python: >=3.7
Requires-Dist: dav-utils (==0.2.*)
